[
  {
    "row": 53,
    "email": "ap4isnou@gmail.com",
    "error": "Failed to upload to storage"
  },
  {
    "row": 79,
    "email": "ozguroguzakkanat@gmail.com",
    "error": "Failed to upload to storage"
  },
  {
    "row": 85,
    "email": "hanna.jalver@gmail.com",
    "error": "Failed to upload to storage"
  },
  {
    "row": 93,
    "email": "fredrik_edstrom@live.se",
    "error": "Failed to upload to storage"
  },
  {
    "row": 94,
    "email": "thallyafranca2022@gmail.com",
    "error": "Failed to upload to storage"
  },
  {
    "row": 154,
    "email": "edyarianio@gmail.com",
    "error": "Failed to upload to storage"
  },
  {
    "row": 242,
    "email": "officeragar@gmail.com",
    "error": "Failed to upload to storage"
  },
  {
    "row": 243,
    "email": "santiagojes@hotmail.com",
    "error": "Failed to upload to storage"
  },
  {
    "row": 255,
    "email": "re.sena4@gmail.com",
    "error": "Failed to upload to storage"
  },
  {
    "row": 263,
    "email": "shyrilcrinos@gmail.com",
    "error": "Failed to upload to storage"
  },
  {
    "row": 276,
    "email": "ines.huteau@gmail.com",
    "error": "Failed to upload to storage"
  },
  {
    "row": 287,
    "email": "saeed.sattari75@gmail.com",
    "error": "Failed to upload to storage"
  }
]